ugly_code/__init__.py
ugly_code/cmd.py
ugly_code/ex.py
ugly_code/tool.py
ugly_code/rabbit/__init__.py
ugly_code/rabbit/define.py
ugly_code/rabbit/listen.py
ugly_code/runit/__init__.py
ugly_code/runit/_tool.py
ugly_code/runit/ctrl.py
ugly_code/runit/extra.py
ugly_code/runit/typing.py
ugly_code/runit/worker.py
ugly_code-0.0.13.dist-info/LICENSE
ugly_code-0.0.13.dist-info/METADATA
ugly_code-0.0.13.dist-info/WHEEL
ugly_code-0.0.13.dist-info/top_level.txt
ugly_code-0.0.13.dist-info/RECORD
