Metadata-Version: 2.1
Name: ugly_code
Version: 0.0.13
Summary: ugly-code tools
Home-page: https://github.com/irealing/ugly-code
Author: MemoryLeak
Author-email: irealing@163.com
License: MIT
Platform: any
Requires-Python: >=3.5
License-File: LICENSE
Provides-Extra: rabbit
Requires-Dist: pika ; extra == 'rabbit'
